zfista/__init__.py
zfista/_typing.py
zfista/metrics.py
zfista/problems.py
zfista/proximal_gradient.py
zfista-0.0.3.dist-info/LICENSE
zfista-0.0.3.dist-info/METADATA
zfista-0.0.3.dist-info/WHEEL
zfista-0.0.3.dist-info/top_level.txt
zfista-0.0.3.dist-info/RECORD
