Metadata-Version: 2.1
Name: zfista
Version: 0.0.3
Summary: A globally convergent fast iterative shrinkage-thresholding algorithm with a new momentum factor for single and multi-objective convex optimization
Author-email: Hiroki Tanabe <tanabe.hiroki.45n@kyoto-u.jp>
License: MIT
Requires-Python: >=3.9
License-File: LICENSE
Requires-Dist: jaxopt
Requires-Dist: pymoo
Requires-Dist: scipy
Requires-Dist: typing-extensions
Provides-Extra: bench
Requires-Dist: joblib; extra == "bench"
Requires-Dist: matplotlib; extra == "bench"
Requires-Dist: pandas; extra == "bench"
Requires-Dist: SciencePlots; extra == "bench"
Requires-Dist: tqdm; extra == "bench"
Provides-Extra: docs
Requires-Dist: sphinx; extra == "docs"
Requires-Dist: sphinxcontrib-katex; extra == "docs"
Requires-Dist: sphinx-rtd-theme; extra == "docs"
Provides-Extra: examples
Requires-Dist: zfista[bench]; extra == "examples"
Requires-Dist: jupyter; extra == "examples"
Requires-Dist: PyWavelets; extra == "examples"
Requires-Dist: scikit-image; extra == "examples"
